{
	"file_path": "C:\\Users\\Lize\\AppData\\Local\\Packages\\Microsoft.MinecraftUWP_8wekyb3d8bbwe\\LocalState\\games\\com.mojang\\development_behavior_packs\\ichor\\blocks\\cruor.json",
	"file_type": "block",
	"format_version": 0,
	"cache_content": {
		"format_version": "1.16.0",
		"minecraft:block": {
			"description": {
				"identifier": "coc:cruor",
				"is_experimental": false
			},
			"components": {
				"minecraft:destroy_time": 1,
				"minecraft:explosion_resistance": 1,
				"minecraft:map_color": "#ffffff"
			}
		}
	},
	"file_uuid": "26baf36b_08a5_4010_8725_1fc40f5a1b44"
}